AUTHOR
LICENSE
MANIFEST.in
README.rst
setup.cfg
setup.py
doc/source/conf.py
doc/source/_static/genibabel.png
doc/source/_static/carousel/chaos_sts_fundamental.png
doc/source/_static/carousel/haplo_cca_multivariate.png
doc/source/_static/carousel/ig_ageing_fundamental.png
doc/source/_static/carousel/ig_in_autism_clinical.png
doc/source/_static/carousel/netscience_structpen.png
doc/source/_static/carousel/priorization_bioinformatics.png
genibabel/__init__.py
genibabel/elasticmetagen.py
genibabel/info.py
genibabel.egg-info/PKG-INFO
genibabel.egg-info/SOURCES.txt
genibabel.egg-info/dependency_links.txt
genibabel.egg-info/requires.txt
genibabel.egg-info/top_level.txt