Metadata-Version: 1.1
Name: genibabel
Version: 1.0.0
Summary: 
